package_dev_utils/__init__.py
package_dev_utils/py.typed
package_dev_utils/tests/__init__.py
package_dev_utils/tests/args/__init__.py
package_dev_utils/tests/args/args.py
package_dev_utils-0.1.6.dist-info/LICENSE
package_dev_utils-0.1.6.dist-info/METADATA
package_dev_utils-0.1.6.dist-info/WHEEL
package_dev_utils-0.1.6.dist-info/top_level.txt
package_dev_utils-0.1.6.dist-info/RECORD
