Metadata-Version: 2.1
Name: package-dev-utils
Version: 0.1.6
Summary: Common development utilities for Python packages
Author-email: Quinten Roets <qdr2104@columbia.edu>
License: MIT
Project-URL: Source Code, https://github.com/quintenroets/package-dev-utils
Requires-Python: >=3.10
License-File: LICENSE
Provides-Extra: dev
Requires-Dist: hypothesis <7,>=6.91 ; extra == 'dev'
Requires-Dist: package-dev-tools <1,>=0.3.1 ; extra == 'dev'
